cloudlift/__init__.py
cloudlift/constants.py
cloudlift/utils.py
cloudlift/config/__init__.py
cloudlift/config/account.py
cloudlift/config/banner.py
cloudlift/config/decimal_encoder.py
cloudlift/config/diff.py
cloudlift/config/dynamodb_configuration.py
cloudlift/config/environment_configuration.py
cloudlift/config/logging.py
cloudlift/config/mfa.py
cloudlift/config/parameter_store.py
cloudlift/config/pre_flight.py
cloudlift/config/region.py
cloudlift/config/service_configuration.py
cloudlift/config/stack.py
cloudlift/config/utils.py
cloudlift/deployment/__init__.py
cloudlift/deployment/changesets.py
cloudlift/deployment/cluster_template_generator.py
cloudlift/deployment/configs.py
cloudlift/deployment/deployer.py
cloudlift/deployment/ecr_client.py
cloudlift/deployment/ecs.py
cloudlift/deployment/editor.py
cloudlift/deployment/environment_creator.py
cloudlift/deployment/progress.py
cloudlift/deployment/service_creator.py
cloudlift/deployment/service_information_fetcher.py
cloudlift/deployment/service_template_generator.py
cloudlift/deployment/service_updater.py
cloudlift/deployment/task_definition_creator.py
cloudlift/deployment/template_generator.py
cloudlift/exceptions/__init__.py
cloudlift/exceptions/exceptions.py
cloudlift/session/__init__.py
cloudlift/session/session_creator.py
cloudlift/version/__init__.py
cloudlift-2.1.1.dist-info/LICENSE
cloudlift-2.1.1.dist-info/METADATA
cloudlift-2.1.1.dist-info/WHEEL
cloudlift-2.1.1.dist-info/entry_points.txt
cloudlift-2.1.1.dist-info/top_level.txt
cloudlift-2.1.1.dist-info/zip-safe
cloudlift-2.1.1.dist-info/RECORD
