Metadata-Version: 2.1
Name: cloudlift
Version: 2.1.1
Summary: Cloudlift makes it easier to launch dockerized services in AWS ECS
Home-page: https://github.com/GetSimpl/cloudlift
Requires-Python: >=3.9
License-File: LICENSE
Requires-Dist: boto3 ==1.34.111
Requires-Dist: awscli ==1.32.111
Requires-Dist: certifi ==2017.7.27.1
Requires-Dist: cfn-flip ==1.0.3
Requires-Dist: chardet ==3.0.4
Requires-Dist: click ==6.7
Requires-Dist: colorclass ==2.2.2
Requires-Dist: dictdiffer ==0.7.0
Requires-Dist: docutils ==0.14
Requires-Dist: future ==0.16.0
Requires-Dist: futures ==3.1.1
Requires-Dist: idna ==2.6
Requires-Dist: jmespath ==0.9.3
Requires-Dist: jsonschema ==2.6.0
Requires-Dist: python-dateutil ==2.8.2
Requires-Dist: requests >=2.20.0
Requires-Dist: six ==1.10.0
Requires-Dist: stringcase ==1.0.6
Requires-Dist: terminaltables ==3.1.0
Requires-Dist: troposphere ==4.5.2
Requires-Dist: awacs ==2.4.0
Requires-Dist: botocore ==1.34.111
